dataclouder_tts/__init__.py
dataclouder_tts/google_tts_service.py
dataclouder_tts/models/tts_models.py
dataclouder_tts/models.py
dataclouder_tts/speech.py
dataclouder_tts/tts_controller.py
dataclouder_tts/tts_service_base.py
dataclouder_tts/whisper/whisper_groq.py
dataclouder_tts/whisper_controller.py
dataclouder_tts-0.0.8.dist-info/METADATA
dataclouder_tts-0.0.8.dist-info/WHEEL
dataclouder_tts-0.0.8.dist-info/RECORD
