Metadata-Version: 2.3
Name: dataclouder_tts
Version: 0.0.8
Summary: TTS library for Dataclouder
License: MIT
Author: adamo jordan
Author-email: adamo.figueroa@gmail.com
Requires-Python: >=3.9
Classifier: License :: OSI Approved :: MIT License
Classifier: Programming Language :: Python :: 3
Classifier: Programming Language :: Python :: 3.9
Classifier: Programming Language :: Python :: 3.10
Classifier: Programming Language :: Python :: 3.11
Classifier: Programming Language :: Python :: 3.12
Classifier: Programming Language :: Python :: 3.13
Requires-Dist: fastapi (>=0.104.0)
Requires-Dist: openai (>=1.3.0)
Requires-Dist: pydantic (>=2.4.2)
